githubcitest/__init__.py
githubcitest/test_class.py
githubcitest-0.5.0.dist-info/METADATA
githubcitest-0.5.0.dist-info/WHEEL
githubcitest-0.5.0.dist-info/top_level.txt
githubcitest-0.5.0.dist-info/RECORD
