Metadata-Version: 2.1
Name: githubcitest
Version: 0.5.0
Summary: No help, dude.
Home-page: https://github.com/phohenecker/ci-test
Author: Patrick Hohenecker
Author-email: patrick.hohenecker@gmx.at
License: BSD-3-Clause
Platform: UNKNOWN
Classifier: Programming Language :: Python :: 3.9
Requires-Python: >=3.9
Requires-Dist: torch (>=1.8.1)
